LICENSE.txt
MANIFEST.in
README.rst
setup.py
Products/__init__.py
Products.MailArchive.egg-info/PKG-INFO
Products.MailArchive.egg-info/SOURCES.txt
Products.MailArchive.egg-info/dependency_links.txt
Products.MailArchive.egg-info/namespace_packages.txt
Products.MailArchive.egg-info/not-zip-safe
Products.MailArchive.egg-info/requires.txt
Products.MailArchive.egg-info/top_level.txt
Products/MailArchive/MailArchive.py
Products/MailArchive/MailArchiveFolder.py
Products/MailArchive/Utils.py
Products/MailArchive/__init__.py
Products/MailArchive/version.txt
Products/MailArchive/icons/folder.gif
Products/MailArchive/icons/sortdown.gif
Products/MailArchive/icons/sortnot.gif
Products/MailArchive/icons/sortup.gif
Products/MailArchive/modules/BLACKWORDS
Products/MailArchive/modules/__init__.py
Products/MailArchive/modules/cleanhtml.py
Products/MailArchive/modules/imap_client.py
Products/MailArchive/modules/mbox.py
Products/MailArchive/modules/mbox_email.py
Products/MailArchive/modules/mbox_filters.py
Products/MailArchive/tests/framework.py
Products/MailArchive/tests/run_tests.bat
Products/MailArchive/tests/run_tests.py
Products/MailArchive/tests/run_tests.sh
Products/MailArchive/tests/test_app.py
Products/MailArchive/tests/test_email.py
Products/MailArchive/tests/data/msg1.txt
Products/MailArchive/tests/data/msg2.txt
Products/MailArchive/tests/data/msg3.txt
Products/MailArchive/tests/data/msg4.txt
Products/MailArchive/tests/data/test.png
Products/MailArchive/tests/data/test.zip
Products/MailArchive/tests/data/mbox_directory/mbox1.mbx
Products/MailArchive/tests/data/mbox_directory/mbox2.mbx
Products/MailArchive/tests/data/mbox_directory/mbox3.mbx
Products/MailArchive/zpt/MailArchiveFolder_add.zpt
Products/MailArchive/zpt/MailArchiveFolder_index.zpt
Products/MailArchive/zpt/MailArchiveFolder_props.zpt
Products/MailArchive/zpt/MailArchiveFolder_xslt.zpt
Products/MailArchive/zpt/MailArchive_index.zpt
Products/MailArchive/zpt/MailArchive_message.zpt
docs/HISTORY.txt
docs/INSTALL.txt
docs/TODO.txt