Metadata-Version: 2.1
Name: Products.MailArchive
Version: 2.0
Summary: Browse a mail archive in Unix MBOX format
Home-page: https://github.com/eea/Products.MailArchive
Author: European Environment Agency (EEA)
Author-email: webadmin@eea.europa.eu
License: GPL
Keywords: eea
Platform: UNKNOWN
Classifier: Framework :: Zope2
Classifier: Programming Language :: Python
Classifier: Topic :: Software Development :: Libraries :: Python Modules
